megdata/__init__.py
megdata/bti_channel.py
megdata/bti_config.py
megdata/bti_dipolefile.py
megdata/bti_elecfile.py
megdata/bti_hsfile.py
megdata/bti_pdf.py
megdata/bti_process.py
megdata/bti_userblocks.py
megdata/common.py
megdata/ctf_dataset.py
megdata/ctf_hc.py
megdata/ctf_mri.py
megdata/ctf_polhemus.py
megdata/ctf_res4.py
megdata/meghdf.py
megdata/test/__init__.py
megdata/test/support.py
megdata/tests/__init__.py
megdata/tests/test_ctfreaders.py
megdata-1.0.3.data/scripts/megdataBTIConfigFile
megdata-1.0.3.data/scripts/megdataBTICreateM4D
megdata-1.0.3.data/scripts/megdataBTIElectrodeFile
megdata-1.0.3.data/scripts/megdataBTIHSFile
megdata-1.0.3.data/scripts/megdataBTIPDF
megdata-1.0.3.data/scripts/megdataBTIToMEGHDF
megdata-1.0.3.data/scripts/megdataCTFDataset
megdata-1.0.3.data/scripts/megdataCTFRes4
megdata-1.0.3.dist-info/DESCRIPTION.rst
megdata-1.0.3.dist-info/METADATA
megdata-1.0.3.dist-info/RECORD
megdata-1.0.3.dist-info/WHEEL
megdata-1.0.3.dist-info/metadata.json
megdata-1.0.3.dist-info/top_level.txt
