Metadata-Version: 2.0
Name: megdata
Version: 1.0.3
Summary: Python MEG data readers
Home-page: https://vcs.ynic.york.ac.uk/naf/python-megdata
Author: Mark Hymers
Author-email: ynic-devel@ynic.york.ac.uk
License: GNU GPL v2 or later
Keywords: MEG,magnetoencephalography
Platform: UNKNOWN
Classifier: Development Status :: 5 - Production/Stable
Classifier: Environment :: Console
Classifier: Intended Audience :: Science/Research
Classifier: License :: OSI Approved :: GNU General Public License v2 or later (GPLv2+)
Classifier: Programming Language :: Python :: 2.7
Classifier: Programming Language :: Python :: 3.5
Classifier: Programming Language :: Python :: 3.6
Classifier: Programming Language :: Python :: 3.7
Classifier: Topic :: Scientific/Engineering :: Bio-Informatics
Classifier: Topic :: Scientific/Engineering :: Medical Science Apps.
Requires-Dist: numpy (>=1.12)
Requires-Dist: scipy (>=0.18)
Provides-Extra: meghdf
Requires-Dist: h5py (>=2.7.0); extra == 'meghdf'
